AUTHORS.txt
LICENSE.txt
MANIFEST.in
README.rst
setup.cfg
setup.py
git_recipe.egg-info/PKG-INFO
git_recipe.egg-info/SOURCES.txt
git_recipe.egg-info/dependency_links.txt
git_recipe.egg-info/entry_points.txt
git_recipe.egg-info/namespace_packages.txt
git_recipe.egg-info/not-zip-safe
git_recipe.egg-info/requires.txt
git_recipe.egg-info/top_level.txt
recipe/__init__.py
recipe/git/__init__.py