Metadata-Version: 1.0
Name: git-recipe
Version: 0.0.4
Summary: Simple buildout recipe for downloading git repositories. It uses system git command and its syntax
Home-page: http://github.com/youngking/git-recipe
Author: Young King
Author-email: yanckin@gmail.com
License: UNKNOWN
Platform: UNKNOWN
Classifier: Development Status :: 3 - Alpha
Classifier: Framework :: Buildout
Classifier: Intended Audience :: Developers
Classifier: License :: Freely Distributable
Classifier: Natural Language :: Russian
Classifier: Operating System :: Microsoft :: Windows
Classifier: Operating System :: Unix
Classifier: Programming Language :: Python :: 2.5
Classifier: Topic :: Software Development :: Version Control
